<?xml version="1.0" encoding="utf-8"?>
<LanguageData>
  <TITAN_No7_AcidThrumbo.label>7号实验体·腐蚀</TITAN_No7_AcidThrumbo.label>
  <TITAN_No7_AcidThrumbo.description>泰坦计划编号7号——毒素代谢替代路径偏移。体液、唾液乃至角的表面覆盖致命混合毒素，拥有完全毒免疫。</TITAN_No7_AcidThrumbo.description>
  <TITAN_No13_SwampThrumbo.label>13号实验体·深渊</TITAN_No13_SwampThrumbo.label>
  <TITAN_No13_SwampThrumbo.description>泰坦计划编号13号——战斗本能强化（限制版）。最危险的衍生体，护甲极低——纯粹的杀戮引擎。</TITAN_No13_SwampThrumbo.description>
  <TITAN_No26_ToyThrumbo.label>26号实验体·亲卫</TITAN_No26_ToyThrumbo.label>
  <TITAN_No26_ToyThrumbo.description>泰坦计划编号26号——社交行为强化（非军事型）。体型仅大型犬大小，零脏污零野性绝不反击。</TITAN_No26_ToyThrumbo.description>
  <TITAN_No42_AuroraThrumbo.label>42号实验体·星辉</TITAN_No42_AuroraThrumbo.label>
  <TITAN_No42_AuroraThrumbo.description>泰坦计划编号42号——极端低温适应+生物发光。-150°C安然入睡，唯一拒绝吃树的实验体。</TITAN_No42_AuroraThrumbo.description>
  <TITAN_No45_FireThrumbo.label>45号实验体·熔炉</TITAN_No45_FireThrumbo.label>
  <TITAN_No45_FireThrumbo.description>泰坦计划编号45号——热能代谢重定向。体核230°C几乎不可燃，每3天产出18单位化合燃料。</TITAN_No45_FireThrumbo.description>
  <TITAN_No50_DesertThrumbo.label>50号实验体·荒魂</TITAN_No50_DesertThrumbo.label>
  <TITAN_No50_DesertThrumbo.description>泰坦计划编号50号——极端代谢节流。饥饿率仅0.25，30天不进食也仅瘦7%。</TITAN_No50_DesertThrumbo.description>
  <TITAN_No64_PrairieThrumbo.label>64号实验体·铁壁</TITAN_No64_PrairieThrumbo.label>
  <TITAN_No64_PrairieThrumbo.description>泰坦计划编号64号——骨骼-角质超矿化。锐甲0.95接近纯钢板，痛阈0.95。与13号一体两面。</TITAN_No64_PrairieThrumbo.description>
  <TITAN_No88_JungleThrumbo.label>88号实验体·繁花</TITAN_No88_JungleThrumbo.label>
  <TITAN_No88_JungleThrumbo.description>泰坦计划编号88号——共生真菌植入+植物代谢旁路。每4天产出4单位草药，Flammability高达1.2——致命的怕火弱点。</TITAN_No88_JungleThrumbo.description>
</LanguageData>
